sgci_resource/__init__.py
sgci_resource/_version.py
sgci_resource/core.py
sgci_resource-0.0.1.dist-info/METADATA
sgci_resource-0.0.1.dist-info/WHEEL
sgci_resource-0.0.1.dist-info/top_level.txt
sgci_resource-0.0.1.dist-info/RECORD
