Metadata-Version: 2.1
Name: sgci-resource
Version: 0.0.1
Summary: SGCI resource catalog API
Home-page: https://github.com/SGCI/sgci-resource-clients
Author: SGCI
Author-email: denphi@denphi.com
License: BSD
Keywords: IPython
Platform: Linux
Platform: Mac OS X
Platform: Windows
Classifier: Intended Audience :: Developers
Classifier: Intended Audience :: Science/Research
Classifier: License :: OSI Approved :: BSD License
Classifier: Programming Language :: Python
Classifier: Programming Language :: Python :: 3
Classifier: Programming Language :: Python :: 3.4
Classifier: Programming Language :: Python :: 3.5
Classifier: Programming Language :: Python :: 3.6
Classifier: Programming Language :: Python :: 3.7
Requires-Dist: paramiko (>=2.7.2)
Requires-Dist: scp (>=0.13.3)
Requires-Dist: PyGithub (>=1.54.1)
Requires-Dist: jmespath (>=0.10.0)
Requires-Dist: jsonschema (>=3.2.0)
Provides-Extra: docs
Provides-Extra: examples
Provides-Extra: test
